pello/__init__.py
pello/__main__.py
pello/pello_greeting.py
Pello-1.0.4.dist-info/LICENSE.txt
Pello-1.0.4.dist-info/METADATA
Pello-1.0.4.dist-info/WHEEL
Pello-1.0.4.dist-info/entry_points.txt
Pello-1.0.4.dist-info/top_level.txt
Pello-1.0.4.dist-info/RECORD
