Metadata-Version: 2.1
Name: Pello
Version: 1.0.4
Summary: An example Python Hello World package
Home-page: https://github.com/fedora-python/Pello
Author: Tomáš Hrnčiar
Author-email: tomas.hrnciar@me.com
License: MIT-0
Classifier: Programming Language :: Python :: 3
Classifier: License :: OSI Approved :: MIT No Attribution License (MIT-0)
Classifier: Operating System :: OS Independent
License-File: LICENSE.txt
Provides-Extra: color
Requires-Dist: blessings ; extra == 'color'
